mercury_package/__init__.py
mercury_package/cli.py
mercury_package/reporting.py
mercury_package/simulator.py
mercury_package/visualization.py
mercury_package/models/__init__.py
mercury_package/models/base_model.py
mercury_package/models/compartmental_model.py
mercury_package/models/empirical_model.py
mercury_package/models/mechanistic_model.py
mercury_package/models/observed_data.py
mercury_package/models/simplified_model.py
mercury_pollution_simulator-1.1.1.dist-info/licenses/LICENSE
mercury_pollution_simulator-1.1.1.dist-info/METADATA
mercury_pollution_simulator-1.1.1.dist-info/WHEEL
mercury_pollution_simulator-1.1.1.dist-info/entry_points.txt
mercury_pollution_simulator-1.1.1.dist-info/top_level.txt
mercury_pollution_simulator-1.1.1.dist-info/RECORD
