Metadata-Version: 2.4
Name: mercury-pollution-simulator
Version: 1.1.1
Summary: Monte Carlo simulator for mercury pollution assessment with multiple model types (empirical, mechanistic, compartmental, simplified)
Home-page: https://github.com/henrynunoo-mensah/mercury-pollution-simulator
Author: Henry Nunoo-Mensah
Author-email: Henry Nunoo-Mensah <hnunoo-mensah@knust.edu.gh>
License: MIT
Keywords: mercury,pollution,monte-carlo,environmental,risk-assessment,transport-model,water-quality,soil-contamination
Classifier: Development Status :: 4 - Beta
Classifier: Intended Audience :: Science/Research
Classifier: Topic :: Scientific/Engineering
Classifier: Topic :: Scientific/Engineering :: Hydrology
Classifier: Topic :: Scientific/Engineering :: Chemistry
Classifier: Topic :: Scientific/Engineering :: Atmospheric Science
Classifier: License :: OSI Approved :: MIT License
Classifier: Programming Language :: Python :: 3
Classifier: Programming Language :: Python :: 3.8
Classifier: Programming Language :: Python :: 3.9
Classifier: Programming Language :: Python :: 3.10
Classifier: Programming Language :: Python :: 3.11
Requires-Python: >=3.8
License-File: LICENSE
Requires-Dist: numpy>=1.21.0
Requires-Dist: scipy>=1.7.0
Requires-Dist: pandas>=1.3.0
Requires-Dist: matplotlib>=3.4.0
Requires-Dist: openpyxl>=3.0.0
Provides-Extra: dev
Requires-Dist: pytest>=7.0.0; extra == "dev"
Requires-Dist: black>=22.0.0; extra == "dev"
Requires-Dist: flake8>=4.0.0; extra == "dev"
Dynamic: author
Dynamic: home-page
Dynamic: license-file
Dynamic: requires-python
